push_receiver/__init__.py
push_receiver/android_fcm_register.py
push_receiver/mcs.py
push_receiver/push_receiver.py
rustPlusPushReceiver-0.6.1.dist-info/METADATA
rustPlusPushReceiver-0.6.1.dist-info/WHEEL
rustPlusPushReceiver-0.6.1.dist-info/top_level.txt
rustPlusPushReceiver-0.6.1.dist-info/RECORD
